pwgen/__init__.py
pwgen/charlists.py
pwgen/wordlist_4k.py
pwgen/exception/__init__.py
pw_generator-0.1.0.dist-info/LICENSE
pw_generator-0.1.0.dist-info/METADATA
pw_generator-0.1.0.dist-info/WHEEL
pw_generator-0.1.0.dist-info/top_level.txt
pw_generator-0.1.0.dist-info/RECORD
