Metadata-Version: 2.1
Name: pw-generator
Version: 0.1.0
Summary: Simple password generator
Home-page: https://github.com/pietro-a/pw-generator
Author: Petr Antonov
Author-email: petr@antonov.space
License: UNKNOWN
Platform: UNKNOWN
Classifier: Programming Language :: Python :: 3
Classifier: License :: OSI Approved :: MIT License
Classifier: Operating System :: OS Independent
Requires-Python: >=3.5
